docs/Makefile
docs/make.bat
docs/source/conf.py
docs/source/index.rst
docs/source/modules.rst
docs/source/write_df.rst
env/bin/rst2html.py
env/bin/rst2html4.py
env/bin/rst2html5.py
env/bin/rst2latex.py
env/bin/rst2man.py
env/bin/rst2odt.py
env/bin/rst2odt_prepstyles.py
env/bin/rst2pseudoxml.py
env/bin/rst2s5.py
env/bin/rst2xetex.py
env/bin/rst2xml.py
env/bin/rstpep2html.py
write_df/__init__.py
write_df/bq_writer.py
write_df/common.py
write_df/nosql_writer.py
write_df/sql_writer.py
df_to_db-2.2.dist-info/LICENSE
df_to_db-2.2.dist-info/METADATA
df_to_db-2.2.dist-info/WHEEL
df_to_db-2.2.dist-info/top_level.txt
df_to_db-2.2.dist-info/RECORD
