Metadata-Version: 2.1
Name: df-to-db
Version: 2.2
Summary: An awesome package that can write pandas dataframe to different databases
Author-email: Masum Billal <billalmasum93@gmail.com>
License: Apache License
Project-URL: Homepage, https://github.com/proafxin/df_to_db
Requires-Python: >=3.6
License-File: LICENSE
Requires-Dist: pandas
Requires-Dist: pymysql
Requires-Dist: cryptography
Requires-Dist: pymongo
Requires-Dist: sqlalchemy (<=1.4.0)
Requires-Dist: requests
Requires-Dist: mysqlclient
Requires-Dist: sphinx
Requires-Dist: sphinx-book-theme
Requires-Dist: sphinx-rtd-theme
Requires-Dist: psycopg2-binary
Requires-Dist: sqlalchemy-utils
Requires-Dist: dnspython
Requires-Dist: pymssql
Requires-Dist: google-cloud-bigquery
Requires-Dist: pyarrow
Provides-Extra: dev
Requires-Dist: pytest ; extra == 'dev'
Requires-Dist: coverage ; extra == 'dev'
Requires-Dist: tox ; extra == 'dev'
Requires-Dist: black ; extra == 'dev'
Requires-Dist: flake8 ; extra == 'dev'
